langgraph_s3_checkpointer-0.1.0.dist-info/licenses/LICENSE
s3checkpointer/__init__.py
s3checkpointer/s3saver.py
langgraph_s3_checkpointer-0.1.0.dist-info/METADATA
langgraph_s3_checkpointer-0.1.0.dist-info/WHEEL
langgraph_s3_checkpointer-0.1.0.dist-info/top_level.txt
langgraph_s3_checkpointer-0.1.0.dist-info/RECORD
