Metadata-Version: 2.4
Name: langgraph-s3-checkpointer
Version: 0.1.0
Summary: Langgraph S3 Checkpoint Persistant Memory
Requires-Python: >=3.10
License-File: LICENSE
Requires-Dist: aiobotocore>=2.25.0
Requires-Dist: boto3>=1.40.49
Requires-Dist: langgraph>=0.6.10
Provides-Extra: examples
Requires-Dist: dotenv>=0.9.9; extra == "examples"
Requires-Dist: ipykernel>=7.0.1; extra == "examples"
Dynamic: license-file
